callable.py
callable-0.1.1.dist-info/DESCRIPTION.rst
callable-0.1.1.dist-info/METADATA
callable-0.1.1.dist-info/RECORD
callable-0.1.1.dist-info/WHEEL
callable-0.1.1.dist-info/metadata.json
callable-0.1.1.dist-info/top_level.txt
