Metadata-Version: 2.0
Name: callable
Version: 0.1.1
Summary: Easy interface to handle callable signature
Home-page: https://github.com/youknowone/callable
Author: Jeong YunWon
Author-email: callable@youknowone.org
License: UNKNOWN
Platform: UNKNOWN
Classifier: Intended Audience :: Developers
Classifier: Operating System :: OS Independent
Classifier: License :: OSI Approved :: BSD License
Classifier: Programming Language :: Python
Classifier: Programming Language :: Python :: 2
Classifier: Programming Language :: Python :: 2.7
Classifier: Programming Language :: Python :: 3
Classifier: Programming Language :: Python :: 3.3
Classifier: Programming Language :: Python :: 3.4
Classifier: Programming Language :: Python :: 3.5
Classifier: Programming Language :: Python :: 3.6
Requires-Dist: attrs (>=16.3)
Provides-Extra: tests
Requires-Dist: pytest (>=3.0.2); extra == 'tests'
Requires-Dist: pytest-asyncio; extra == 'tests'
Requires-Dist: pytest-cov; extra == 'tests'
